macsensors.cpython-311-darwin.so
mactemperatures/__init__.py
mactemperatures/core.py
mactemperatures/exceptions.py
mactemperatures-0.0.2.dist-info/LICENSE
mactemperatures-0.0.2.dist-info/METADATA
mactemperatures-0.0.2.dist-info/WHEEL
mactemperatures-0.0.2.dist-info/top_level.txt
mactemperatures-0.0.2.dist-info/RECORD
