Metadata-Version: 2.1
Name: mactemperatures
Version: 0.0.2
Summary: Python Package for Obtaining Temperature Sensor Readings on M1 Macs
Home-page: https://github.com/joshunrau/mac-temperatures
Author: Joshua Unrau
Author-email: contact@joshuaunrau.com
Project-URL: Bug Tracker, https://github.com/joshunrau/mac-temperatures/issues
Classifier: Programming Language :: C
Classifier: Programming Language :: Python :: 3
Classifier: License :: OSI Approved :: MIT License
Classifier: Operating System :: MacOS
Requires-Python: >=3.7
License-File: LICENSE
